ansiconv.py
setup.py
ansiconv.egg-info/PKG-INFO
ansiconv.egg-info/SOURCES.txt
ansiconv.egg-info/dependency_links.txt
ansiconv.egg-info/requires.txt
ansiconv.egg-info/top_level.txt
test/test_ansiconv.py